ezpanos/__init__.py
ezpanos/ezpanos.py
ezpanos/factories.py
ezpanos/models.py
ezpanos/panos_cache.py
ezpanos/utils.py
ezpanos-0.2.3.dist-info/licenses/LICENSE
ezpanos-0.2.3.dist-info/METADATA
ezpanos-0.2.3.dist-info/WHEEL
ezpanos-0.2.3.dist-info/top_level.txt
ezpanos-0.2.3.dist-info/RECORD
