Metadata-Version: 2.4
Name: ezpanos
Version: 0.2.3
Summary: A lightweight PanOS (Palo Alto Netoworks) firewall Management utility.
Author: Noah Black
Keywords: panorama,panos,palo alto networks,automation,remote-execution,batch,infrastructure,control-plane
Classifier: Development Status :: 4 - Beta
Classifier: Intended Audience :: Developers
Classifier: Topic :: System :: Systems Administration
Classifier: Topic :: Software Development :: Libraries
Classifier: Programming Language :: Python :: 3
Requires-Python: >=3.9
License-File: LICENSE
Requires-Dist: requests
Requires-Dist: ezssh
Dynamic: license-file
